vertica_python/__init__.py
vertica_python/compat.py
vertica_python/datatypes.py
vertica_python/errors.py
vertica_python/os_utils.py
vertica_python/tests/__init__.py
vertica_python/tests/conftest.py
vertica_python/tests/common/__init__.py
vertica_python/tests/common/base.py
vertica_python/tests/integration_tests/__init__.py
vertica_python/tests/integration_tests/base.py
vertica_python/tests/integration_tests/test_authentication.py
vertica_python/tests/integration_tests/test_cancel.py
vertica_python/tests/integration_tests/test_column.py
vertica_python/tests/integration_tests/test_connection.py
vertica_python/tests/integration_tests/test_cursor.py
vertica_python/tests/integration_tests/test_datatypes.py
vertica_python/tests/integration_tests/test_dates.py
vertica_python/tests/integration_tests/test_errors.py
vertica_python/tests/integration_tests/test_loadbalance.py
vertica_python/tests/integration_tests/test_timezones.py
vertica_python/tests/integration_tests/test_tls.py
vertica_python/tests/integration_tests/test_transfer_format.py
vertica_python/tests/integration_tests/test_unicode.py
vertica_python/tests/unit_tests/__init__.py
vertica_python/tests/unit_tests/base.py
vertica_python/tests/unit_tests/test_errors.py
vertica_python/tests/unit_tests/test_logging.py
vertica_python/tests/unit_tests/test_notice.py
vertica_python/tests/unit_tests/test_parsedsn.py
vertica_python/tests/unit_tests/test_sql_literal.py
vertica_python/tests/unit_tests/test_timestamps.py
vertica_python/vertica/__init__.py
vertica_python/vertica/column.py
vertica_python/vertica/connection.py
vertica_python/vertica/cursor.py
vertica_python/vertica/deserializer.py
vertica_python/vertica/log.py
vertica_python/vertica/messages/__init__.py
vertica_python/vertica/messages/message.py
vertica_python/vertica/messages/backend_messages/__init__.py
vertica_python/vertica/messages/backend_messages/authentication.py
vertica_python/vertica/messages/backend_messages/backend_key_data.py
vertica_python-1.3.8.dist-info/AUTHORS
vertica_python-1.3.8.dist-info/LICENSE
vertica_python-1.3.8.dist-info/METADATA
vertica_python-1.3.8.dist-info/WHEEL
vertica_python-1.3.8.dist-info/top_level.txt
vertica_python-1.3.8.dist-info/RECORD
