Metadata-Version: 2.1
Name: vertica-python
Version: 1.3.8
Summary: Official native Python client for the Vertica database.
Home-page: https://github.com/vertica/vertica-python
Author: Justin Berka, Alex Kim, Siting Ren
Author-email: justin.berka@gmail.com, alex.kim@uber.com, sitingren@hotmail.com
License: Apache License 2.0
Keywords: database vertica
Platform: UNKNOWN
Classifier: Development Status :: 5 - Production/Stable
Classifier: Intended Audience :: Developers
Classifier: License :: OSI Approved :: Apache Software License
Classifier: Programming Language :: Python
Classifier: Programming Language :: Python :: 3
Classifier: Programming Language :: Python :: 3.7
Classifier: Programming Language :: Python :: 3.8
Classifier: Programming Language :: Python :: 3.9
Classifier: Programming Language :: Python :: 3.10
Classifier: Programming Language :: Python :: 3.11
Classifier: Programming Language :: Python :: 3.12
Classifier: Topic :: Database
Classifier: Topic :: Database :: Database Engines/Servers
Classifier: Topic :: Database :: Front-Ends
Classifier: Topic :: Software Development :: Libraries :: Python Modules
Classifier: Operating System :: OS Independent
Requires-Python: >=3.7
